Metadata-Version: 2.1
Name: django-site-local-middleware
Version: 2020.7.1
Summary: adds .local:port to the site domain links for local development if settings.DEBUG is True
Home-page: https://github.com/andrewp-as-is/django-site-local-middleware.py
License: Unlicense
Keywords: django site middleware
Platform: UNKNOWN
Classifier: Framework :: Django
Classifier: License :: Public Domain
Classifier: Operating System :: OS Independent
Classifier: Programming Language :: Python :: 3
